{
  "annotations": {
    "list": []
  },
  "editable": true,
  "fiscalYearStartMonth": 0,
  "graphTooltip": 0,
  "id": null,
  "links": [],
  "liveNow": false,
  "panels": [
    {
      "datasource": {
        "type": "influxdb",
        "uid": "${DS_SFC}"
      },
      "fieldConfig": {
        "defaults": {
          "color": {
            "mode": "palette-classic"
          },
          "custom": {
            "axisLabel": "",
            "axisPlacement": "auto",
            "barAlignment": 0,
            "drawStyle": "line",
            "fillOpacity": 0,
            "gradientMode": "none",
            "hideFrom": {
              "legend": false,
              "tooltip": false,
              "vis": false
            },
            "lineInterpolation": "linear",
            "lineWidth": 1,
            "pointSize": 5,
            "scaleDistribution": {
              "type": "linear"
            },
            "showPoints": "auto",
            "spanNulls": false,
            "stacking": {
              "group": "A",
              "mode": "none"
            },
            "thresholdsStyle": {
              "mode": "off"
            }
          },
          "mappings": [],
          "thresholds": {
            "mode": "absolute",
            "steps": [
              {
                "color": "green",
                "value": null
              },
              {
                "color": "red",
                "value": 80
              }
            ]
          }
        },
        "overrides": []
      },
      "gridPos": {
        "h": 9,
        "w": 12,
        "x": 0,
        "y": 0
      },
      "id": 1,
      "options": {
        "legend": {
          "calcs": [],
          "displayMode": "list",
          "placement": "bottom",
          "showLegend": true
        },
        "tooltip": {
          "mode": "single",
          "sort": "none"
        }
      },
      "targets": [
        {
          "dataset": "iox",
          "datasource": {
            "type": "influxdb",
            "uid": "${DS_SFC}"
          },
          "editorMode": "code",
          "format": "time_series",
          "rawQuery": true,
          "rawSql": "SELECT time, actual_iops, cluster, name, 'raw' as resolution FROM volume_performance WHERE time >= $__timeFrom AND time <= $__timeTo AND (('$cluster' = '$__all') OR (cluster = '$cluster')) AND (('$volume' = '*') OR (name = '$volume')) ORDER BY time",
          "refId": "A"
        },
        {
          "dataset": "iox",
          "datasource": {
            "type": "influxdb",
            "uid": "${DS_SFC}"
          },
          "editorMode": "code",
          "format": "time_series",
          "rawQuery": true,
          "rawSql": "SELECT time, actual_iops_avg as actual_iops, cluster, name, '5m' as resolution FROM volume_performance_5m_auto WHERE time >= $__timeFrom AND time <= $__timeTo AND (('$cluster' = '$__all') OR (cluster = '$cluster')) AND (('$volume' = '*') OR (name = '$volume')) ORDER BY time",
          "refId": "B",
          "hide": false
        }
      ],
      "title": "Volume IOPS Performance",
      "type": "timeseries"
    }
  ],
  "schemaVersion": 39,
  "tags": [
    "SFC"
  ],
  "templating": {
    "list": [
      {
        "current": {
          "selected": false,
          "text": "All",
          "value": "$__all"
        },
        "datasource": {
          "type": "influxdb",
          "uid": "${DS_SFC}"
        },
        "definition": "",
        "hide": 0,
        "includeAll": true,
        "label": "Cluster",
        "multi": false,
        "name": "cluster",
        "options": [],
        "query": "SELECT DISTINCT cluster FROM volume_performance ORDER BY cluster",
        "refresh": 1,
        "regex": "",
        "skipUrlSync": false,
        "sort": 1,
        "type": "query"
      },
      {
        "allValue": "*",
        "current": {
          "selected": false,
          "text": "All",
          "value": "$__all"
        },
        "datasource": {
          "type": "influxdb",
          "uid": "${DS_SFC}"
        },
        "definition": "",
        "hide": 0,
        "includeAll": true,
        "label": "Volume",
        "multi": false,
        "name": "volume",
        "options": [],
        "query": "SELECT DISTINCT name FROM volume_performance WHERE CASE WHEN '$cluster' = '$__all' THEN true ELSE cluster = '$cluster' END ORDER BY name",
        "refresh": 1,
        "regex": "",
        "skipUrlSync": false,
        "sort": 1,
        "type": "query"
      }
    ]
  },
  "time": {
    "from": "now-1h",
    "to": "now"
  },
  "timepicker": {},
  "timezone": "browser",
  "title": "SFC Volume Performance - Raw vs 5min Downsampled (DS01 Demo)",
  "uid": "",
  "version": 1
}